nbwrite/cli.py
nbwrite/config.py
nbwrite/constants.py
nbwrite/index.py
nbwrite/writer.py
nbwrite-0.2.dist-info/LICENSE
nbwrite-0.2.dist-info/METADATA
nbwrite-0.2.dist-info/WHEEL
nbwrite-0.2.dist-info/entry_points.txt
nbwrite-0.2.dist-info/RECORD
